{
  "version": "1.1.1",
  "windows": {
    "main": {
      "main": true,
      "url": "app://editor/index.html",
      "windowType": "dockable",
      "x": 4,
      "y": 23,
      "width": 1916,
      "height": 1057,
      "layout": {
        "children": [
          {
            "children": [
              {
                "active": 0,
                "children": [
                  "hierarchy"
                ],
                "height": 445,
                "type": "panel",
                "width": 354
              },
              {
                "active": 0,
                "children": [
                  "assets"
                ],
                "height": 518,
                "type": "panel",
                "width": 354
              }
            ],
            "height": 966,
            "type": "dock-v",
            "width": 354
          },
          {
            "children": [
              {
                "children": [
                  {
                    "active": 0,
                    "children": [
                      "scene"
                    ],
                    "height": 622,
                    "type": "panel",
                    "width": 800
                  },
                  {
                    "active": 0,
                    "children": [
                      "node-library"
                    ],
                    "height": 622,
                    "type": "panel",
                    "width": 369
                  }
                ],
                "height": 622,
                "type": "dock-h",
                "width": 1172
              },
              {
                "active": 0,
                "children": [
                  "console",
                  "timeline"
                ],
                "height": 341,
                "type": "panel",
                "width": 1172
              }
            ],
            "height": 966,
            "type": "dock-v",
            "width": 1172
          },
          {
            "active": 0,
            "children": [
              "inspector"
            ],
            "height": 966,
            "type": "panel",
            "width": 378
          }
        ],
        "type": "dock-h"
      },
      "panels": [
        "console",
        "inspector",
        "hierarchy",
        "assets",
        "scene",
        "node-library",
        "timeline"
      ]
    },
    "window-1493111917619": {
      "main": false,
      "url": "unpack://static/window.html",
      "windowType": "dockable",
      "x": 595,
      "y": 123,
      "width": 500,
      "height": 722,
      "layout": {
        "children": [
          {
            "active": 0,
            "children": [
              "builder"
            ],
            "height": 700,
            "type": "panel",
            "width": 500
          }
        ],
        "type": "dock-v"
      },
      "panels": [
        "builder"
      ]
    }
  },
  "panels": {
    "code-editor": {
      "x": 238,
      "y": 77,
      "width": 800,
      "height": 622
    },
    "ui-kit": {
      "x": 675,
      "y": 197,
      "width": 800,
      "height": 622
    },
    "package-manager": {
      "x": 485,
      "y": 108,
      "width": 504,
      "height": 777
    },
    "project-settings": {
      "x": 474,
      "y": 58,
      "width": 584,
      "height": 548
    },
    "builder": {
      "x": 595,
      "y": 123,
      "width": 500,
      "height": 722
    },
    "sprite-editor": {
      "x": 872,
      "y": 110,
      "width": 500,
      "height": 522
    },
    "timeline.event": {
      "x": 758,
      "y": 317,
      "width": 400,
      "height": 422
    },
    "store": {
      "x": 558,
      "y": 217,
      "width": 800,
      "height": 622
    },
    "ui-kit-preview": {
      "x": 558,
      "y": 217,
      "width": 800,
      "height": 622
    },
    "tester": {
      "x": 708,
      "y": 117,
      "width": 500,
      "height": 822
    }
  }
}